mdpilot/__init__.py
mdpilot-0.0.1.dist-info/METADATA
mdpilot-0.0.1.dist-info/WHEEL
mdpilot-0.0.1.dist-info/entry_points.txt
mdpilot-0.0.1.dist-info/licenses/LICENSE
mdpilot-0.0.1.dist-info/RECORD
